datastructures/Linear/CDLL.py
datastructures/Linear/CSLL.py
datastructures/Linear/DLL.py
datastructures/Linear/LLQueue.py
datastructures/Linear/LLStack.py
datastructures/Linear/SLL.py
datastructures/Linear/__init__.py
datastructures/nodes/Dnode.py
datastructures/nodes/TNode.py
datastructures/nodes/__init__.py
datastructures/trees/AVL.py
datastructures/trees/BST.py
datastructures/trees/__init__.py
mypythonlib/__init__.py
mypythonlib/myfunctions.py
datastructresLionelEric-2.1.dist-info/METADATA
datastructresLionelEric-2.1.dist-info/WHEEL
datastructresLionelEric-2.1.dist-info/top_level.txt
datastructresLionelEric-2.1.dist-info/RECORD
