Metadata-Version: 2.1
Name: datastructresLionelEric
Version: 2.1
Summary: My first Python library
Author: Me
License: MIT
